aspose/html/__init__.pyi
aspose/html/accessibility/__init__.pyi
aspose/html/accessibility/results/__init__.pyi
aspose/html/accessibility/saving/__init__.pyi
aspose/html/collections/__init__.pyi
aspose/html/converters/__init__.pyi
aspose/html/diagnostics/__init__.pyi
aspose/html/dom/__init__.pyi
aspose/html/dom/attributes/__init__.pyi
aspose/html/dom/canvas/__init__.pyi
aspose/html/dom/css/__init__.pyi
aspose/html/dom/events/__init__.pyi
aspose/html/dom/mutations/__init__.pyi
aspose/html/dom/svg/__init__.pyi
aspose/html/dom/svg/datatypes/__init__.pyi
aspose/html/dom/svg/events/__init__.pyi
aspose/html/dom/svg/filters/__init__.pyi
aspose/html/dom/svg/paths/__init__.pyi
aspose/html/dom/svg/saving/__init__.pyi
aspose/html/dom/traversal/__init__.pyi
aspose/html/dom/traversal/filters/__init__.pyi
aspose/html/dom/views/__init__.pyi
aspose/html/dom/xpath/__init__.pyi
aspose/html/drawing/__init__.pyi
aspose/html/forms/__init__.pyi
aspose/html/io/__init__.pyi
aspose/html/loading/__init__.pyi
aspose/html/net/__init__.pyi
aspose/html/net/headers/__init__.pyi
aspose/html/net/messagefilters/__init__.pyi
aspose/html/net/messagehandlers/__init__.pyi
aspose/html/rendering/__init__.pyi
aspose/html/rendering/doc/__init__.pyi
aspose/html/rendering/fonts/__init__.pyi
aspose/html/rendering/image/__init__.pyi
aspose/html/rendering/pdf/__init__.pyi
aspose/html/rendering/pdf/encryption/__init__.pyi
aspose/html/rendering/xps/__init__.pyi
aspose/html/saving/__init__.pyi
aspose/html/saving/resourcehandlers/__init__.pyi
aspose/html/services/__init__.pyi
aspose/html/toolkit/__init__.pyi
aspose/html/toolkit/markdown/__init__.pyi
aspose/html/toolkit/markdown/syntax/__init__.pyi
aspose/html/toolkit/markdown/syntax/extensions/__init__.pyi
aspose/html/toolkit/markdown/syntax/parser/__init__.pyi
aspose/html/toolkit/markdown/syntax/parser/extensions/__init__.pyi
aspose/html/toolkit/markdown/syntax/parser/extensions/gfm/__init__.pyi
aspose/html/toolkit/markdown/syntax/text/__init__.pyi
aspose_html_net-26.1.0.dist-info/METADATA
aspose_html_net-26.1.0.dist-info/WHEEL
aspose_html_net-26.1.0.dist-info/entry_points.txt
aspose_html_net-26.1.0.dist-info/top_level.txt
aspose_html_net-26.1.0.dist-info/RECORD
