Metadata-Version: 2.1
Name: aspose-html-net
Version: 26.1.0
Summary: Aspose.HTML for Python via .NET is a powerful API for Python that provides a headless browser functionality, allowing you to work with HTML documents in a variety of ways. With this API, you can easily create new HTML documents or open existing ones from different sources. Once you have the document, you can perform various manipulation operations, such as removing and replacing HTML nodes.
Home-page: https://products.aspose.com/html/python-net/
Author: Aspose
License: UNKNOWN
Project-URL: Docs, https://docs.aspose.com/html/python-net/
Project-URL: Release Notes, https://releases.aspose.com/html/python-net/release-notes/2026/aspose-html-for-python-via-dotnet-26-1-release-notes/
Project-URL: Demos, https://products.aspose.app/html/applications
Project-URL: API Reference, https://reference.aspose.com/html/python-net/
Project-URL: Examples, https://github.com/aspose-html/
Project-URL: Blog, https://blog.aspose.com/category/html/
Project-URL: Free Support, https://forum.aspose.com/c/html/29
Project-URL: Temporary License, https://purchase.aspose.com/temporary-license
Keywords: Aspose,Aspose.HTML,Aspose.Total,Python,Component,Conholdate,Conholdate.Total,convert,converter,vectorization,vectorizer,vectorize,encoding,base64,css,DOM,dom-manipulation,image,JPEG,Library,Microsoft,mvc,net-standard,netcore,netstandard,to PDF,PNG,rotate,security,Standard,XPath,XPS,SVG,Windows,Vector Graphics,line,Bezier Curves,Cubic,Glyphs,Paths,Text,Scaling,Rotation,Skewing,Fill,Dots,Bitmap,HTML,HTML-to-Image,HTML-to-PDF,HTML-to-XPS,HTML-to-DOCX,HTML-to-MHTML,HTML-to-Markdown,HTML-to
Platform: macos_arm64
Classifier: Operating System :: Microsoft :: Windows
Classifier: Operating System :: POSIX :: Linux
Classifier: Operating System :: MacOS :: MacOS X
Classifier: License :: Other/Proprietary License
Classifier: Programming Language :: Python :: 3
Classifier: Programming Language :: Python :: 3 :: Only
Classifier: Programming Language :: Python :: 3.8
Classifier: Programming Language :: Python :: 3.9
Classifier: Programming Language :: Python :: 3.10
Classifier: Programming Language :: Python :: 3.11
Classifier: Programming Language :: Python :: 3.12
Classifier: Programming Language :: Python :: 3.13
Classifier: Topic :: Software Development :: Libraries
Classifier: Topic :: Office/Business
Classifier: Topic :: Office/Business :: Scheduling
Requires-Python: >=3.5,<3.14
